{"stats":{"minecraft:custom":{"minecraft:time_since_rest":29470,"minecraft:crouch_one_cm":652,"minecraft:play_time":98368,"minecraft:sprint_one_cm":17991,"minecraft:damage_taken":40,"minecraft:walk_one_cm":30779,"minecraft:deaths":6,"minecraft:sneak_time":2668,"minecraft:drop":2,"minecraft:jump":146,"minecraft:damage_dealt":35,"minecraft:leave_game":7,"minecraft:time_since_death":29429,"minecraft:enchant_item":10,"minecraft:total_world_time":98368,"minecraft:fly_one_cm":443684},"minecraft:used":{"minecraft:netherite_sword":12,"minecraft:ender_eye":9,"minecraft:enchanting_table":1,"minecraft:bookshelf":19,"minecraft:netherite_leggings":1,"minecraft:end_crystal":40,"minecraft:command_block":1,"minecraft:red_bed":117,"minecraft:white_bed":107,"minecraft:light_blue_bed":55,"minecraft:netherite_boots":1,"minecraft:bedrock":5},"minecraft:mined":{"minecraft:grass_block":1},"minecraft:dropped":{"minecraft:red_bed":1,"minecraft:bedrock":1},"minecraft:picked_up":{"minecraft:book":118,"minecraft:enchanting_table":1,"minecraft:netherite_boots":4,"minecraft:netherite_sword":3,"minecraft:enchanted_book":7,"minecraft:ender_eye":1,"minecraft:bookshelf":1,"minecraft:netherite_chestplate":2,"minecraft:light_blue_bed":1,"minecraft:end_crystal":10,"minecraft:netherite_leggings":4,"minecraft:red_bed":1,"minecraft:ender_pearl":1}},"DataVersion":4082}