{"minecraft:recipes/decorations/crafting_table":{"criteria":{"unlock_right_away":"2025-03-14 20:37:21 +0000"},"done":true},"minecraft:adventure/adventuring_time":{"criteria":{"minecraft:taiga":"2025-03-14 21:20:58 +0000","minecraft:plains":"2025-03-14 20:37:22 +0000"},"done":false},"minecraft:story/follow_ender_eye":{"criteria":{"in_stronghold":"2025-03-14 21:21:29 +0000"},"done":true},"minecraft:recipes/decorations/end_crystal":{"criteria":{"has_ender_eye":"2025-03-14 21:26:16 +0000"},"done":true},"minecraft:recipes/decorations/ender_chest":{"criteria":{"has_ender_eye":"2025-03-14 21:26:16 +0000"},"done":true},"minecraft:end/root":{"criteria":{"entered_end":"2025-03-14 21:26:27 +0000"},"done":true},"minecraft:story/enter_the_end":{"criteria":{"entered_end":"2025-03-14 21:26:27 +0000"},"done":true},"minecraft:end/respawn_dragon":{"criteria":{"summoned_dragon":"2025-03-14 21:32:20 +0000"},"done":true},"minecraft:nether/netherite_armor":{"criteria":{"netherite_armor":"2025-03-14 21:52:50 +0000"},"done":true},"minecraft:story/enchant_item":{"criteria":{"enchanted_item":"2025-03-14 22:04:14 +0000"},"done":true},"minecraft:recipes/decorations/chest":{"criteria":{"has_lots_of_items":"2025-03-14 22:05:29 +0000"},"done":true},"minecraft:recipes/building_blocks/bookshelf":{"criteria":{"has_book":"2025-03-14 22:07:28 +0000"},"done":true},"minecraft:recipes/redstone/lectern":{"criteria":{"has_book":"2025-03-14 22:07:28 +0000"},"done":true},"minecraft:recipes/building_blocks/chiseled_bookshelf":{"criteria":{"has_book":"2025-03-14 22:07:28 +0000"},"done":true},"minecraft:recipes/misc/writable_book":{"criteria":{"has_book":"2025-03-14 22:07:28 +0000"},"done":true},"DataVersion":4082}